Metadata-Version: 1.1
Name: FibonacciGenerator
Version: 0.1.2
Summary: A python package for calculating fibonacci numbers
Home-page: UNKNOWN
Author: Snehan Biswas
Author-email: snehanb24118836@gmail.com
License: MIT
Platform: UNKNOWN
Classifier: Development Status :: 5 - Production/Stable
Classifier: Intended Audience :: Education
Classifier: Operating System :: Microsoft :: Windows :: Windows 10
Classifier: License :: OSI Approved :: MIT License
Classifier: Programming Language :: Python :: 3
